README.rst
setup.py
DoraClient/__init__.py
DoraClient.egg-info/PKG-INFO
DoraClient.egg-info/SOURCES.txt
DoraClient.egg-info/dependency_links.txt
DoraClient.egg-info/top_level.txt
DoraClient/bin/__init__.py
DoraClient/bin/dora_client
DoraClient/bin/dora_update
DoraClient/custom/__init__.py
DoraClient/custom/cpu_used.py
DoraClient/custom/df_used.py
DoraClient/custom/last_ip.py
DoraClient/custom/load_used.py
DoraClient/custom/mem_used.py
DoraClient/tools/__init__.py
DoraClient/tools/client.py
DoraClient/tools/config.py
DoraClient/tools/logged.py
DoraClient/tools/update.py
DoraClient/tools/wget.py