Metadata-Version: 1.0
Name: DoraClient
Version: 0.1.2
Summary: monitor client
Home-page: https://github.com/x0hcker/dora-client
Author: x0hcker@gmail.com
Author-email: x0hcker@gmail.com
License: Apache Licence 2.0
Keywords: monitor,DoraClient
Platform: any
